CHANGELOG.md
LICENSE
clown_sort/__init__.py
clown_sort/config.py
clown_sort/filename_extractor.py
clown_sort/files/image_file.py
clown_sort/files/pdf_file.py
clown_sort/files/sortable_file.py
clown_sort/name_images.py
clown_sort/sorter.py
clown_sort/sorting_rules/crypto.csv
clown_sort/util/argument_parser.py
clown_sort/util/dict_helper.py
clown_sort/util/filesystem_helper.py
clown_sort/util/logging.py
clown_sort/util/rich_helper.py
clown_sort/util/string_helper.py
clonwn_sort-0.4.0.dist-info/LICENSE
clonwn_sort-0.4.0.dist-info/WHEEL
clonwn_sort-0.4.0.dist-info/entry_points.txt
clonwn_sort-0.4.0.dist-info/METADATA
clonwn_sort-0.4.0.dist-info/RECORD
