Metadata-Version: 2.1
Name: clonwn-sort
Version: 0.4.0
Summary: Sort screenshots based on rules or through individual review.
Home-page: https://github.com/michelcrypt4d4mus/clown_sort
Keywords: ocr,organization,organizer,screenshot,rename,sort
Author: Michel de Cryptadamus
Author-email: michel@cryptadamus.com
Requires-Python: >=3.10,<4.0
Classifier: Programming Language :: Python :: 3
Classifier: Programming Language :: Python :: 3.10
Classifier: Programming Language :: Python :: 3.11
Classifier: Topic :: Desktop Environment :: File Managers
Classifier: Topic :: Multimedia :: Graphics :: Capture
Classifier: Topic :: Multimedia :: Graphics :: Capture :: Screen Capture
Classifier: Topic :: Scientific/Engineering :: Image Processing
Requires-Dist: PySimpleGUI (>=4.60.4,<5.0.0)
Requires-Dist: exif (>=1.5.0,<2.0.0)
Requires-Dist: filedate (>=2.0,<3.0)
Requires-Dist: piexif (>=1.1.3,<2.0.0)
Requires-Dist: pillow (>=9.4.0,<10.0.0)
Requires-Dist: pyexiftool (>=0.5.5,<0.6.0)
Requires-Dist: pypdf (>=3.4.1,<4.0.0)
Requires-Dist: pytesseract (>=0.3.10,<0.4.0)
Requires-Dist: python-dotenv (>=0.21.1,<0.22.0)
Requires-Dist: rich (>=13.0.1,<14.0.0)
Requires-Dist: rich-argparse-plus (>=0.3.1.4,<0.4.0.0)
